README.md
setup.py
LibPythonPro_Atila.egg-info/PKG-INFO
LibPythonPro_Atila.egg-info/SOURCES.txt
LibPythonPro_Atila.egg-info/dependency_links.txt
LibPythonPro_Atila.egg-info/not-zip-safe
LibPythonPro_Atila.egg-info/requires.txt
LibPythonPro_Atila.egg-info/top_level.txt
libpythonpro/__init__.py
libpythonpro/github_api.py